is3_python_sdk/__init__.py
is3_python_sdk/config/__init__.py
is3_python_sdk/config/config_model.py
is3_python_sdk/custom/__init__.py
is3_python_sdk/custom/execute.py
is3_python_sdk/custom/iS3PythonCore.py
is3_python_sdk/custom/test_data_base.py
is3_python_sdk/data_query/__init__.py
is3_python_sdk/data_query/is3_python_api.py
is3_python_sdk/domain/__init__.py
is3_python_sdk/domain/data_dto.py
is3_python_sdk/domain/task_data.py
is3_python_sdk/is3_kafka/__init__.py
is3_python_sdk/is3_kafka/kafka_execute.py
is3_python_sdk/task/__init__.py
is3_python_sdk/task/heartbeat.py
is3_python_sdk/utils/__init__.py
is3_python_sdk/utils/create_data_entity.py
is3_python_sdk/utils/fileUtil.py
is3_python_sdk/utils/is3_request_util.py
is3_python_sdk/utils/kafka_component_util.py
is3_python_sdk/utils/log_util.py
is3_python_sdk/utils/logger.py
is3_sdk-0.0.9.dist-info/licenses/LICENSE
is3_sdk-0.0.9.dist-info/METADATA
is3_sdk-0.0.9.dist-info/WHEEL
is3_sdk-0.0.9.dist-info/entry_points.txt
is3_sdk-0.0.9.dist-info/top_level.txt
is3_sdk-0.0.9.dist-info/RECORD
