Metadata-Version: 2.4
Name: iS3_sdk
Version: 0.0.9
Summary: is3 python sdk
Home-page: https://github.com/your-org/is3_python_sdk
Author: chaser
Author-email: lzkqcc@tongji.edu.cn
Classifier: Programming Language :: Python :: 3
Classifier: License :: OSI Approved :: MIT License
Classifier: Operating System :: OS Independent
License-File: LICENSE
Requires-Dist: colorama<1,>=0.4.6
Requires-Dist: Flask<4,>=3.0
Requires-Dist: pydantic<3,>=2.9
Requires-Dist: confluent_kafka<3,>=2.3
Requires-Dist: requests<3,>=2.31
Requires-Dist: websocket-client<2,>=1.6
Dynamic: author
Dynamic: author-email
Dynamic: classifier
Dynamic: description
Dynamic: description-content-type
Dynamic: home-page
Dynamic: license-file
Dynamic: requires-dist
Dynamic: summary
